build/lib/poezio_omemo/__init__.py
build/lib/poezio_omemo/__main__.py
build/lib/poezio_omemo/core.py
build/lib/poezio_omemo/py.typed
build/lib/poezio_omemo/version.py
poezio_omemo/__init__.py
poezio_omemo/__main__.py
poezio_omemo/core.py
poezio_omemo/py.typed
poezio_omemo/version.py
poezio_omemo-0.8.0.dist-info/licenses/LICENSE
poezio_omemo-0.8.0.dist-info/METADATA
poezio_omemo-0.8.0.dist-info/WHEEL
poezio_omemo-0.8.0.dist-info/entry_points.txt
poezio_omemo-0.8.0.dist-info/top_level.txt
poezio_omemo-0.8.0.dist-info/RECORD
