Metadata-Version: 2.4
Name: poezio-omemo
Version: 0.8.0
Summary: OMEMO plugin for Poezio
Author-email: "Maxime Buquet (pep.)" <pep@bouah.net>, "Tim Henkes (Syndace)" <me@syndace.dev>
Maintainer-email: "Tim Henkes (Syndace)" <me@syndace.dev>
License-Expression: GPL-3.0-only
Project-URL: Repository, https://codeberg.org/poezio/poezio-omemo
Project-URL: Issues, https://codeberg.org/poezio/poezio-omemo/issues
Project-URL: Changelog, https://codeberg.org/poezio/poezio-omemo/src/branch/main/CHANGELOG.md
Classifier: Development Status :: 3 - Alpha
Classifier: Programming Language :: Python :: 3
Classifier: Programming Language :: Python :: 3 :: Only
Classifier: Programming Language :: Python :: 3.9
Classifier: Programming Language :: Python :: 3.10
Classifier: Programming Language :: Python :: 3.11
Classifier: Programming Language :: Python :: 3.12
Classifier: Programming Language :: Python :: 3.13
Classifier: Intended Audience :: Developers
Classifier: Topic :: Communications :: Chat
Classifier: Topic :: Internet :: XMPP
Classifier: Topic :: Security :: Cryptography
Classifier: Topic :: Software Development :: Libraries :: Python Modules
Requires-Python: >=3.9
License-File: LICENSE
Requires-Dist: slixmpp-omemo>=2.0.0
Provides-Extra: lint
Requires-Dist: mypy; extra == "lint"
Requires-Dist: pylint; extra == "lint"
Requires-Dist: flake8; extra == "lint"
Requires-Dist: flake8-pyproject; extra == "lint"
Provides-Extra: dev
Requires-Dist: poezio-omemo[lint]; extra == "dev"
Dynamic: license-file
